eem_django/__init__.py
eem_django/apps.py
eem_django/models.py
eem_django/tests.py
eem_django/templatetags/__init__.py
eem_django/templatetags/eem.py
eem_django-0.0.0.dist-info/DESCRIPTION.rst
eem_django-0.0.0.dist-info/METADATA
eem_django-0.0.0.dist-info/RECORD
eem_django-0.0.0.dist-info/WHEEL
eem_django-0.0.0.dist-info/metadata.json
eem_django-0.0.0.dist-info/top_level.txt
