Metadata-Version: 2.0
Name: eem-django
Version: 0.0.0
Summary: Django app providing a template tag to create "eem" image manipulation URLs.
Home-page: https://github.com/eemagery
Author: eemagery
Author-email: UNKNOWN
License: MIT
Keywords: django image photo manipulate crop resize eem
Platform: UNKNOWN
Classifier: Development Status :: 3 - Alpha
Classifier: Environment :: Web Environment
Classifier: Framework :: Django
Classifier: Intended Audience :: Developers
Classifier: License :: OSI Approved :: MIT License
Classifier: Programming Language :: Python :: 2
Classifier: Programming Language :: Python :: 2.7
Classifier: Programming Language :: Python :: 3
Classifier: Programming Language :: Python :: 3.3
Classifier: Programming Language :: Python :: 3.4
Classifier: Programming Language :: Python :: 3.5
Requires-Dist: eem-py
